deepthink/__init__.py
deepthink/activations.py
deepthink/history.py
deepthink/layers.py
deepthink/loss.py
deepthink/metrics.py
deepthink/model.py
deepthink/optimizers.py
deepthink/utils.py
deepthink-0.2.1.dist-info/LICENSE
deepthink-0.2.1.dist-info/METADATA
deepthink-0.2.1.dist-info/WHEEL
deepthink-0.2.1.dist-info/top_level.txt
deepthink-0.2.1.dist-info/RECORD
