Metadata-Version: 2.1
Name: deepthink
Version: 0.2.1
Summary: Deep Learning library
Home-page: https://github.com/Caff1982/DeepThink
Author: Stephen Cafferty
Author-email: stephencafferty@hotmail.com
License: MIT
Classifier: Development Status :: 3 - Alpha
Classifier: License :: OSI Approved :: MIT License
Classifier: Operating System :: POSIX :: Linux
Classifier: Programming Language :: Python :: 3
Classifier: Programming Language :: Python :: 3.9
License-File: LICENSE
Requires-Dist: numpy (>=1.22.3)
Requires-Dist: matplotlib (>=3.6.2)
Requires-Dist: scikit-learn (>=1.1.2)
Requires-Dist: tqdm (>=4.64.1)
Requires-Dist: pandas (>=1.4.1)
